CHANGES.rst
MANIFEST.in
README.rst
pyproject.toml
src/emeraldtree/ElementInclude.py
src/emeraldtree/ElementPath.py
src/emeraldtree/ElementTree.py
src/emeraldtree/__init__.py
src/emeraldtree/_version.py
src/emeraldtree/html.py
src/emeraldtree/tree.py
src/emeraldtree.egg-info/PKG-INFO
src/emeraldtree.egg-info/SOURCES.txt
src/emeraldtree.egg-info/dependency_links.txt
src/emeraldtree.egg-info/top_level.txt
src/emeraldtree/tests/__init__.py
src/emeraldtree/tests/test_html.py
src/emeraldtree/tests/test_tree.py