Metadata-Version: 2.1
Name: emeraldtree
Version: 0.11.0
Summary: EmeraldTree - a light-weight XML object model for Python.
Author-email: Bastian Blank <bblank@thinkmo.de>
Maintainer-email: Thomas Waldmann <tw@waldmann-edv.de>
License: Python (MIT style)
Project-URL: Homepage, https://github.com/moinwiki/emeraldtree
Keywords: xml,html,html5,polyglot,element,tree,dom,unicode
Classifier: Development Status :: 4 - Beta
Classifier: Operating System :: OS Independent
Classifier: Programming Language :: Python
Classifier: Programming Language :: Python :: 3
Classifier: Programming Language :: Python :: 3.9
Classifier: Programming Language :: Python :: 3.10
Classifier: Programming Language :: Python :: 3.11
Classifier: Programming Language :: Python :: 3.12
Classifier: License :: OSI Approved :: Python Software Foundation License
Classifier: Intended Audience :: Developers
Classifier: Topic :: Text Processing :: Markup :: HTML
Classifier: Topic :: Text Processing :: Markup :: XML
Requires-Python: >=3.9
